pyflagoras/__init__.py
pyflagoras/__main__.py
pyflagoras/flag_info.py
pyflagoras/image_processor.py
pyflagoras/pyflagoras.py
pyflagoras/similarity_algorithms.py
pyflagoras/utils.py
pyflagoras/data/colour_aliases.json
pyflagoras/data/flag_aliases.json
pyflagoras/flags/agender_2014.json
pyflagoras/flags/aroace_2018.json
pyflagoras/flags/aromantic_2014.json
pyflagoras/flags/asexual_2010.json
pyflagoras/flags/bear_1995.json
pyflagoras/flags/bigender_2014.json
pyflagoras/flags/bisexual_1998.json
pyflagoras/flags/gay_men_2019.json
pyflagoras/flags/genderfluid_2012.json
pyflagoras/flags/genderqueer_2011.json
pyflagoras/flags/intersexInclusive_2021.json
pyflagoras/flags/intersex_2013.json
pyflagoras/flags/labrysLesbian_1999.json
pyflagoras/flags/lesbian_2010.json
pyflagoras/flags/lesbian_2018.json
pyflagoras/flags/lesbian_2019.json
pyflagoras/flags/lipstick_lesbian_2010.json
pyflagoras/flags/nonbinary_2014.json
pyflagoras/flags/omnisexual_2015.json
pyflagoras/flags/pangender_2015.json
pyflagoras/flags/pansexual_2010.json
pyflagoras/flags/philadelphiaPride_2017.json
pyflagoras/flags/pinkUnionJack_2009.json
pyflagoras/flags/polysexual_2012.json
pyflagoras/flags/pride_1978_eightStripes.json
pyflagoras/flags/pride_1978_sevenStripes.json
pyflagoras/flags/pride_1979.json
pyflagoras/flags/progressPride_2018.json
pyflagoras/flags/sapphic_2015.json
pyflagoras/flags/southAfricaPride_2010.json
pyflagoras/flags/transgender_1999.json
pyflagoras/flags/twink_2009.json
pyflagoras-0.5.4.dist-info/LICENSE
pyflagoras-0.5.4.dist-info/METADATA
pyflagoras-0.5.4.dist-info/WHEEL
pyflagoras-0.5.4.dist-info/entry_points.txt
pyflagoras-0.5.4.dist-info/top_level.txt
pyflagoras-0.5.4.dist-info/RECORD
