Metadata-Version: 2.1
Name: pyflagoras
Version: 0.5.4
Summary: A Python command line interface tool for theming .svg files using user-provided images.
Author-email: Annabel Quach <annabelquach13@gmail.com>
Project-URL: Homepage, https://github.com/phthallo/pyflagoras
Project-URL: Bug Tracker, https://github.com/phthallo/pyflagoras/issues
Classifier: Programming Language :: Python :: 3
Classifier: License :: OSI Approved :: MIT License
Classifier: Operating System :: OS Independent
Classifier: Development Status :: 2 - Pre-Alpha
Requires-Python: >=3.10
License-File: LICENSE
Requires-Dist: pillow >=10.3.0
Requires-Dist: pymupdf >=1.24.7
Requires-Dist: svglib >=1.5.1
Requires-Dist: numpy >=2.0.0
